seletools/__init__.py
seletools/actions.py
seletools/drag_and_drop.js
seletools/indexeddb.py
seletools/localstorage.py
seletools/waits.py
seletools-1.5.0.dist-info/LICENSE
seletools-1.5.0.dist-info/METADATA
seletools-1.5.0.dist-info/WHEEL
seletools-1.5.0.dist-info/top_level.txt
seletools-1.5.0.dist-info/RECORD
