Metadata-Version: 2.1
Name: seletools
Version: 1.5.0
Summary: Helpful tools for Selenium on Python
Home-page: https://github.com/bormando/selenium-tools
Author: Dmitrii Bormotov
Author-email: squier7@gmail.com
License: MIT
Classifier: Programming Language :: Python :: 3
Classifier: License :: OSI Approved :: MIT License
Classifier: Operating System :: OS Independent
Requires-Python: >=3.8
License-File: LICENSE
